pytest_git_fixtures/__init__.py
pytest_git_fixtures/fixtures.py
pytest_git_fixtures/git-debug.sh
pytest_git_fixtures/git-init.sh
pytest_git_fixtures/gitconfig
pytest_git_fixtures/utils.py
tests/__init__.py
tests/test_fixtures.py
tests/test_utils.py
pytest_git_fixtures-0.1.7.dist-info/LICENSE.md
pytest_git_fixtures-0.1.7.dist-info/METADATA
pytest_git_fixtures-0.1.7.dist-info/WHEEL
pytest_git_fixtures-0.1.7.dist-info/entry_points.txt
pytest_git_fixtures-0.1.7.dist-info/top_level.txt
pytest_git_fixtures-0.1.7.dist-info/RECORD
