Metadata-Version: 2.1
Name: pytest-git-fixtures
Version: 0.1.7
Summary: Pytest fixtures for testing with git.
Home-page: https://github.com/crashvb/pytest-git-fixtures
Author: Richard Davis
Author-email: crashvb@gmail.com
License: GNU General Public License v3.0
Keywords: fixtures git git-scm pytest
Platform: UNKNOWN
Classifier: Development Status :: 4 - Beta
Classifier: Intended Audience :: Developers
Classifier: License :: OSI Approved :: Apache Software License
Classifier: Programming Language :: Python :: 3
Classifier: Operating System :: OS Independent
Requires-Dist: pytest
Requires-Dist: pytest-gnupg-fixtures
Provides-Extra: dev
Requires-Dist: black ; extra == 'dev'
Requires-Dist: pylint ; extra == 'dev'
Requires-Dist: twine ; extra == 'dev'
Requires-Dist: wheel ; extra == 'dev'
